setup.py
dirwatcher/__init__.py
dirwatcher/core.py
dirwatcher/main.py
dirwatcher.egg-info/PKG-INFO
dirwatcher.egg-info/SOURCES.txt
dirwatcher.egg-info/dependency_links.txt
dirwatcher.egg-info/entry_points.txt
dirwatcher.egg-info/requires.txt
dirwatcher.egg-info/top_level.txt