Metadata-Version: 1.1
Name: dirwatcher
Version: 0.2
Summary: Watch directory to reload script on file changes
Home-page: https://github.com/linkdd/dirwatcher
Author: David Delassus
Author-email: david.jose.delassus@gmail.com
License: MIT
Keywords: directory watcher livereload
Platform: UNKNOWN
Classifier: Development Status :: 3 - Alpha
Classifier: License :: OSI Approved :: MIT License
Classifier: Topic :: Utilities
Classifier: Operating System :: OS Independent
Classifier: Programming Language :: Python
Classifier: Programming Language :: Python :: 3
Classifier: Programming Language :: Python :: 3.4
Classifier: Programming Language :: Python :: 3.5
Classifier: Programming Language :: Python :: 3.6
Classifier: Programming Language :: Python :: Implementation :: CPython
